pylxca/__init__.py
pylxca/pylxca_api/__init__.py
pylxca/pylxca_api/lxca_api.py
pylxca/pylxca_api/lxca_connection.py
pylxca/pylxca_api/lxca_logger.conf
pylxca/pylxca_api/lxca_rest.py
pylxca/pylxca_cmd/__init__.py
pylxca/pylxca_cmd/lxca_cmd.py
pylxca/pylxca_cmd/lxca_cmd_data.json
pylxca/pylxca_cmd/lxca_filters.xml
pylxca/pylxca_cmd/lxca_icommands.py
pylxca/pylxca_cmd/lxca_ishell.py
pylxca/pylxca_cmd/lxca_pyshell.py
pylxca/pylxca_cmd/lxca_view.py
pylxca/test/pylxca_unittest
pylxca-4.2.0.data/scripts/lxca_shell
pylxca-4.2.0.dist-info/LICENSE
pylxca-4.2.0.dist-info/METADATA
pylxca-4.2.0.dist-info/WHEEL
pylxca-4.2.0.dist-info/top_level.txt
pylxca-4.2.0.dist-info/RECORD
