Metadata-Version: 2.1
Name: pylxca
Version: 4.2.0
Summary: It is tool/api to connect LXCA from command line
Home-page: http://www.lenovo.com
Author: Girish Kumar, Prashant Bhosle
Author-email: gkumar1@lenovo.com, pbhosle@lenovo.com
License: Apache License 2.0
Keywords: PYLXCA
Classifier: Development Status :: 3 - Alpha
Classifier: Topic :: Utilities
Classifier: License :: OSI Approved :: Apache Software License
License-File: LICENSE
Requires-Dist: requests >=2.7.0
Requires-Dist: requests-toolbelt >=0.8.0
Requires-Dist: unittest2
